firewalla_api_d2/__init__.py
firewalla_api_d2/get_all_boxes.py
firewalla_api_d2/get_all_devices.py
firewalla_api_d2-0.0.31.dist-info/LICENSE
firewalla_api_d2-0.0.31.dist-info/METADATA
firewalla_api_d2-0.0.31.dist-info/WHEEL
firewalla_api_d2-0.0.31.dist-info/top_level.txt
firewalla_api_d2-0.0.31.dist-info/RECORD
